fz_word_finder/__init__.py
fz_word_finder/finder.py
fz_word_finder/helpers.py
fz_word_finder/tries.py
fz_word_finder/variant_tools.py
fz_word_finder-0.0.8.dist-info/METADATA
fz_word_finder-0.0.8.dist-info/WHEEL
fz_word_finder-0.0.8.dist-info/top_level.txt
fz_word_finder-0.0.8.dist-info/RECORD
