Metadata-Version: 2.1
Name: fz-word-finder
Version: 0.0.8
Summary: Fuzzy match word finder. Supports multiple simultaneous target strings and fuzzy match rules. (No regex or normalization)
Home-page: https://github.com/Rairye/fz-word-finder
Download-URL: https://github.com/Rairye/fz-word-finder/archive/refs/tags/v0.0.8.tar.gz
Author: Rairye
License: apache-2.0
Keywords: fuzzy,match,search
Platform: UNKNOWN
Classifier: Development Status :: 3 - Alpha
Classifier: Intended Audience :: End Users/Desktop
Classifier: Intended Audience :: Developers
Classifier: License :: OSI Approved :: Apache Software License
Classifier: Programming Language :: Python :: 3
Classifier: Programming Language :: Python :: 3.1
Classifier: Programming Language :: Python :: 3.2
Classifier: Programming Language :: Python :: 3.3
Classifier: Programming Language :: Python :: 3.4
Classifier: Programming Language :: Python :: 3.5
Classifier: Programming Language :: Python :: 3.6
Classifier: Programming Language :: Python :: 3.7
